{
  "openapi": "3.0.0",
  "info": {
    "title": "PFS2 - API",
    "description": "API criada utilizando o padrão REST na disciplina de Programação Fullstack 2",
    "version": "1.0.0"
  },
  "servers": [
    {
      "url": "http://localhost:5000/"
    }
  ],
  "paths": {
    "/": {
      "get": {
        "tags": [
          "Home"
        ],
        "summary": "Endpoint para a home do site",
        "description": "",
        "responses": {
          "default": {
            "description": ""
          }
        }
      }
    },
    "/projects/": {
      "get": {
        "description": "",
        "responses": {
          "default": {
            "description": ""
          }
        }
      }
    }
  },
  "components": {
    "securitySchemes": {
      "bearerAuth": {
        "type": "http",
        "scheme": "bearer"
      }
    }
  }
}